pyams_auth_remote/__init__.py
pyams_auth_remote/include.py
pyams_auth_remote/interfaces.py
pyams_auth_remote/plugin.py
pyams_auth_remote/doctests/README.rst
pyams_auth_remote/locales/pyams_auth_remote.pot
pyams_auth_remote/locales/fr/LC_MESSAGES/pyams_auth_remote.mo
pyams_auth_remote/locales/fr/LC_MESSAGES/pyams_auth_remote.po
pyams_auth_remote/tests/__init__.py
pyams_auth_remote/tests/test_utilsdocs.py
pyams_auth_remote/tests/test_utilsdocstrings.py
pyams_auth_remote-2.1.2.dist-info/LICENSE
pyams_auth_remote-2.1.2.dist-info/METADATA
pyams_auth_remote-2.1.2.dist-info/WHEEL
pyams_auth_remote-2.1.2.dist-info/namespace_packages.txt
pyams_auth_remote-2.1.2.dist-info/top_level.txt
pyams_auth_remote-2.1.2.dist-info/RECORD
