Metadata-Version: 2.1
Name: pyams-auth-remote
Version: 2.1.2
Summary: PyAMS authentication package using REMOTE_USER environment variable
Home-page: https://pyams.readthedocs.io
Author: Thierry Florac
Author-email: tflorac@ulthar.net
License: ZPL
Keywords: Pyramid PyAMS
Classifier: License :: OSI Approved :: Zope Public License
Classifier: Development Status :: 4 - Beta
Classifier: Programming Language :: Python
Classifier: Framework :: Pyramid
Classifier: Topic :: Software Development :: Libraries :: Python Modules
License-File: LICENSE
Requires-Dist: setuptools
Requires-Dist: pyams-security >=2.3.4
Requires-Dist: pyams-utils
Requires-Dist: pyramid >=2.0.0
Provides-Extra: test
Requires-Dist: pyams-layer ; extra == 'test'
